{"packages/cupertino_icons/assets/CupertinoIcons.ttf":["packages/cupertino_icons/assets/CupertinoIcons.ttf"],"assets/player_icons/baby_daisy.png":["assets/player_icons/baby_daisy.png"],"assets/player_icons/baby_luigi.png":["assets/player_icons/baby_luigi.png"],"assets/player_icons/baby_mario.png":["assets/player_icons/baby_mario.png"],"assets/player_icons/baby_peach.png":["assets/player_icons/baby_peach.png"],"assets/player_icons/baby_rosalina.png":["assets/player_icons/baby_rosalina.png"],"assets/background.jpg":["assets/background.jpg"],"assets/player_icons/bowser.png":["assets/player_icons/bowser.png"],"assets/player_icons/bowser_jr.png":["assets/player_icons/bowser_jr.png"],"assets/player_icons/cat_peach.png":["assets/player_icons/cat_peach.png"],"assets/player_icons/daisy.png":["assets/player_icons/daisy.png"],"lang/de.json":["lang/de.json"],"assets/player_icons/donkey_kong.png":["assets/player_icons/donkey_kong.png"],"assets/player_icons/dry_bones.png":["assets/player_icons/dry_bones.png"],"assets/player_icons/dry_bowser.png":["assets/player_icons/dry_bowser.png"],"lang/en.json":["lang/en.json"],"assets/player_icons/gold_mario.png":["assets/player_icons/gold_mario.png"],"assets/welcome_page/icon_flat.png":["assets/welcome_page/icon_flat.png"],"assets/welcome_page/icon_material.png":["assets/welcome_page/icon_material.png"],"assets/player_icons/iggy.png":["assets/player_icons/iggy.png"],"assets/player_icons/inkling_blue.png":["assets/player_icons/inkling_blue.png"],"assets/player_icons/inkling_cyan.png":["assets/player_icons/inkling_cyan.png"],"assets/player_icons/inkling_green.png":["assets/player_icons/inkling_green.png"],"assets/player_icons/inkling_orange.png":["assets/player_icons/inkling_orange.png"],"assets/player_icons/inkling_pink.png":["assets/player_icons/inkling_pink.png"],"assets/player_icons/inkling_purple.png":["assets/player_icons/inkling_purple.png"],"assets/player_icons/isabelle.png":["assets/player_icons/isabelle.png"],"assets/player_icons/king_boo.png":["assets/player_icons/king_boo.png"],"assets/player_icons/koopa.png":["assets/player_icons/koopa.png"],"assets/player_icons/lakitu.png":["assets/player_icons/lakitu.png"],"assets/player_icons/larry.png":["assets/player_icons/larry.png"],"assets/player_icons/lemmy.png":["assets/player_icons/lemmy.png"],"assets/player_icons/link.png":["assets/player_icons/link.png"],"assets/player_icons/link_botw.png":["assets/player_icons/link_botw.png"],"assets/player_icons/ludwig.png":["assets/player_icons/ludwig.png"],"assets/player_icons/luigi.png":["assets/player_icons/luigi.png"],"assets/player_icons/mario.png":["assets/player_icons/mario.png"],"assets/player_icons/metal_mario.png":["assets/player_icons/metal_mario.png"],"assets/player_icons/mii.png":["assets/player_icons/mii.png"],"assets/player_icons/mii_amiibo.png":["assets/player_icons/mii_amiibo.png"],"assets/player_icons/morton.png":["assets/player_icons/morton.png"],"packages/wakelock_web/assets/no_sleep.js":["packages/wakelock_web/assets/no_sleep.js"],"assets/player_icons/peach.png":["assets/player_icons/peach.png"],"assets/player_icons/pink_gold_peach.png":["assets/player_icons/pink_gold_peach.png"],"assets/welcome_page/placement_points.png":["assets/welcome_page/placement_points.png"],"assets/positions/position1.png":["assets/positions/position1.png"],"assets/positions/position10.png":["assets/positions/position10.png"],"assets/positions/position11.png":["assets/positions/position11.png"],"assets/positions/position12.png":["assets/positions/position12.png"],"assets/positions/position2.png":["assets/positions/position2.png"],"assets/positions/position3.png":["assets/positions/position3.png"],"assets/positions/position4.png":["assets/positions/position4.png"],"assets/positions/position5.png":["assets/positions/position5.png"],"assets/positions/position6.png":["assets/positions/position6.png"],"assets/positions/position7.png":["assets/positions/position7.png"],"assets/positions/position8.png":["assets/positions/position8.png"],"assets/positions/position9.png":["assets/positions/position9.png"],"assets/race_flag.png":["assets/race_flag.png"],"assets/player_icons/rosalina.png":["assets/player_icons/rosalina.png"],"assets/player_icons/roy.png":["assets/player_icons/roy.png"],"assets/player_icons/secret.png":["assets/player_icons/secret.png"],"assets/player_icons/shy_guy.png":["assets/player_icons/shy_guy.png"],"assets/player_icons/shy_guy_black.png":["assets/player_icons/shy_guy_black.png"],"assets/player_icons/shy_guy_blue.png":["assets/player_icons/shy_guy_blue.png"],"assets/player_icons/shy_guy_green.png":["assets/player_icons/shy_guy_green.png"],"assets/player_icons/shy_guy_light_blue.png":["assets/player_icons/shy_guy_light_blue.png"],"assets/player_icons/shy_guy_orange.png":["assets/player_icons/shy_guy_orange.png"],"assets/player_icons/shy_guy_pink.png":["assets/player_icons/shy_guy_pink.png"],"assets/player_icons/shy_guy_white.png":["assets/player_icons/shy_guy_white.png"],"assets/player_icons/shy_guy_yellow.png":["assets/player_icons/shy_guy_yellow.png"],"assets/player_icons/tanooki_mario.png":["assets/player_icons/tanooki_mario.png"],"assets/player_icons/toad.png":["assets/player_icons/toad.png"],"assets/player_icons/toadette.png":["assets/player_icons/toadette.png"],"assets/player_icons/villager.png":["assets/player_icons/villager.png"],"assets/player_icons/villager_female.png":["assets/player_icons/villager_female.png"],"assets/player_icons/villager_male.png":["assets/player_icons/villager_male.png"],"assets/player_icons/waluigi.png":["assets/player_icons/waluigi.png"],"assets/player_icons/wario.png":["assets/player_icons/wario.png"],"assets/player_icons/wendy.png":["assets/player_icons/wendy.png"],"assets/player_icons/yoshi.png":["assets/player_icons/yoshi.png"],"assets/player_icons/yoshi_black.png":["assets/player_icons/yoshi_black.png"],"assets/player_icons/yoshi_blue.png":["assets/player_icons/yoshi_blue.png"],"assets/player_icons/yoshi_light_blue.png":["assets/player_icons/yoshi_light_blue.png"],"assets/player_icons/yoshi_orange.png":["assets/player_icons/yoshi_orange.png"],"assets/player_icons/yoshi_pink.png":["assets/player_icons/yoshi_pink.png"],"assets/player_icons/yoshi_red.png":["assets/player_icons/yoshi_red.png"],"assets/player_icons/yoshi_white.png":["assets/player_icons/yoshi_white.png"],"assets/player_icons/yoshi_yellow.png":["assets/player_icons/yoshi_yellow.png"]}